aftercopy.py
aftercopy-0.1.1.dist-info/LICENSE
aftercopy-0.1.1.dist-info/METADATA
aftercopy-0.1.1.dist-info/WHEEL
aftercopy-0.1.1.dist-info/entry_points.txt
aftercopy-0.1.1.dist-info/top_level.txt
aftercopy-0.1.1.dist-info/RECORD
