Metadata-Version: 2.1
Name: aftercopy
Version: 0.1.1
Summary: A helper tool that processes text copied from PDF, removing newlines, replacing punctuation and more.
Home-page: https://github.com/coolspring8/aftercopy
Author: CoolSpring8
Author-email: coolspring888@gmail.com
License: UNKNOWN
Project-URL: Bug Reports, https://github.com/coolspring8/aftercopy/issues
Project-URL: Source, https://github.com/coolspring8/aftercopy/
Keywords: clipboard text
Platform: UNKNOWN
Classifier: Development Status :: 3 - Alpha
Classifier: Intended Audience :: End Users/Desktop
Classifier: Topic :: Utilities
Classifier: License :: OSI Approved :: BSD License
Classifier: Programming Language :: Python :: 3
Classifier: Programming Language :: Python :: 3.5
Classifier: Programming Language :: Python :: 3.6
Classifier: Programming Language :: Python :: 3.7
Classifier: Programming Language :: Python :: 3.8
Classifier: Programming Language :: Python :: 3 :: Only
Requires-Python: >=3.5, <4
Requires-Dist: click (>=7.0)
Requires-Dist: pyperclip (>=1.8.0)
